ais_client/__init__.py
ais_client/client.py
ais_client-0.1.0.dist-info/METADATA
ais_client-0.1.0.dist-info/WHEEL
ais_client-0.1.0.dist-info/top_level.txt
ais_client-0.1.0.dist-info/RECORD
