Metadata-Version: 2.4
Name: ais-client
Version: 0.1.0
Summary: Python client for AI Immune System (AIS): JSON firewall + guarded LLM fallback.
Author: Odin Secure
License: Apache-2.0
Project-URL: Homepage, https://www.odinsecure.ai
Project-URL: Repository, https://github.com/Maverick0351a/ai-immune-system
Project-URL: Issues, https://github.com/Maverick0351a/ai-immune-system/issues
Keywords: json,llm,validation,firewall,openai,stripe,guardrails
Classifier: Programming Language :: Python :: 3
Classifier: Programming Language :: Python :: 3 :: Only
Classifier: Programming Language :: Python :: 3.9
Classifier: License :: OSI Approved :: Apache Software License
Classifier: Intended Audience :: Developers
Classifier: Topic :: Software Development :: Libraries :: Python Modules
Classifier: Topic :: Internet :: WWW/HTTP
Requires-Python: >=3.9
Requires-Dist: requests<3,>=2.31.0
